{
  "overview_type": "concept",
  "overview_pacing": {
    "pacing_type": "minutes",
    "pacing_amount": 90
  },
  "overview_labels": [
    {
      "overview_label_type": "session",
      "overview_label_prefix": "2",
      "overview_label_title": "Sessions"
    }
  ],
  "overview_metadata": {
    "overview_number": 11,
    "overview_title": "Tic-Tac-Bingo",
    "overview_subtitle": "Creating Linear Equations and Systems",
    "overview_description": "In this lesson, students create a Tic-Tac-Bingo gameboard with spaces for different types of solutions and then play a game where they join their expression with classmates’ expressions to create equations with different types of solutions. Students then solve problems with and without context using substitution."
  },
  "overview_items": [
    {
      "overview_item_type": "learning_goals",
      "overview_item_content_type": "html",
      "overview_item_title": "My Learning Goals",
      "overview_item_data": {
        "overview_item_data_type": "list",
        "overview_item_data_items": [
          "I can solve linear equations with rational coefficients and variables on both sides.",
          "I can solve examples of linear equations with one solution, no solutions, or infinitely many solutions.",
          "I can solve a system of equations algebraically using substitution.",
          "I can interpret a solution to a system of linear equations in terms of the problem situation."
        ]
      }
    },
    {
      "overview_item_type": "big_ideas",
      "overview_item_content_type": "text",
      "overview_item_title": "Big Idea",
      "overview_item_data": {
        "overview_item_data_type": "list",
        "overview_item_data_items": [
          "Linear Equations",
          "Multiple Representations of Functions"
        ]
      }
    },
    {
      "overview_item_type": "essential_ideas",
      "overview_item_content_type": "html",
      "overview_item_title": "Essential Ideas",
      "overview_item_data": {
        "overview_item_data_type": "list",
        "overview_item_data_items": [
          "You can write a system of linear equations given their graphs.",
          "You can create equations with various solutions based on the relationship between the expressions on each side of the equals sign.",
          "You can solve a real-world problem by writing a system of equations, solving the system using substitution, and interpreting the solution.",
          "You can use the substitution method to solve a system of linear equations regardless of the form of the equations."
        ]
      }
    },
    {
      "overview_item_type": "key_terms",
      "overview_item_content_type": "text",
      "overview_item_title": "Key Terms",
      "overview_item_data": {
        "overview_item_data_type": "group_list",
        "overview_item_data_items": [
          {
            "overview_item_data_group_title": "Activity 1",
            "overview_item_data_group_items": []
          },
          {
            "overview_item_data_group_title": "Activity 2",
            "overview_item_data_group_items": []
          }
        ]
      }
    },
    {
      "overview_item_type": "pacing_guide",
      "overview_item_content_type": "text",
      "overview_item_title": "Lesson Structure and Pacing Guide",
      "overview_item_data": {
        "overview_item_data_type": "session_list",
        "overview_item_data_items": [
          {
            "overview_item_data_group_title": "Session 1",
            "overview_item_data_groups": [
              {
                "overview_item_data_group_title": "Activate",
                "overview_item_data_group_items": [
                  {
                    "overview_item_data_group_item_type": "presentation",
                    "overview_item_data_group_item_title": "Line Up for Inspection!",
                    "overview_item_data_group_item_description": "Students create a system of linear equations graphically with given criteria.",
                    "overview_item_data_group_item_pacing": {
                      "pacing_type": "minutes",
                      "pacing_amount": 15
                    }
                  }
                ]
              },
              {
                "overview_item_data_group_title": "Explore and Develop",
                "overview_item_data_group_items": [
                  {
                    "overview_item_data_group_item_type": "book",
                    "overview_item_data_group_item_prefix": "Activity 1",
                    "overview_item_data_group_item_title": "The Tic-Tac-Bingo Game",
                    "overview_item_data_group_item_description": "Students create a Tic-Tac-Bingo gameboard with spaces for different types of solutions.",
                    "overview_item_data_group_item_pacing": {
                      "pacing_type": "minutes",
                      "pacing_amount": 25
                    }
                  }
                ]
              },
              {
                "overview_item_data_group_title": "Reflect",
                "overview_item_data_group_items": [
                  {
                    "overview_item_data_group_item_type": "book",
                    "overview_item_data_group_item_title": "Exit Ticket Procedures",
                    "overview_item_data_group_item_description": "The Substitution Train",
                    "overview_item_data_group_item_pacing": {
                      "pacing_type": "minutes",
                      "pacing_amount": 10
                    }
                  }
                ]
              }
            ]
          },
          {
            "overview_item_data_group_title": "Session 2",
            "overview_item_data_groups": [
              {
                "overview_item_data_group_title": "Explore and Develop",
                "overview_item_data_group_items": [
                  {
                    "overview_item_data_group_item_type": "book",
                    "overview_item_data_group_item_prefix": "Activity 2",
                    "overview_item_data_group_item_title": "Solving Systems by Substitution",
                    "overview_item_data_group_item_description": "Students use substitution to solve each system and interpret the solution in the context of the situation.",
                    "overview_item_data_group_item_pacing": {
                      "pacing_type": "minutes",
                      "pacing_amount": 30
                    }
                  }
                ]
              },
              {
                "overview_item_data_group_title": "Reflect",
                "overview_item_data_group_items": [
                  {
                    "overview_item_data_group_item_type": "book",
                    "overview_item_data_group_item_title": "Exit Ticket Procedures",
                    "overview_item_data_group_item_description": "The Substitution Train",
                    "overview_item_data_group_item_pacing": {
                      "pacing_type": "minutes",
                      "pacing_amount": 10
                    }
                  }
                ]
              }
            ]
          }
        ]
      }
    },
    {
      "overview_item_type": "materials_needed",
      "overview_item_content_type": "text",
      "overview_item_title": "Materials Needed",
      "overview_item_data": {
        "overview_item_data_type": "list",
        "overview_item_data_items": [
          "The Tic-Tac-Bingo Game Answer Matrix (1 per teacher)",
          "The Tic-Tac-Bingo Game Expressions Cards (1 set per class)",
          "The Tic-Tac-Bingo Game Gameboard",
          "If facilitating this lesson without student devices, no additional materials are needed.",
          "To avoid printing additional materials not included in MATHbook (like Activate activities and Session Quick Checks) project them using the Present button above."
        ]
      }
    }
  ]
}