{
  "overview_type": "concept",
  "overview_pacing": {
    "pacing_type": "minutes",
    "pacing_amount": 90
  },
  "overview_labels": [
    {
      "overview_label_type": "session",
      "overview_label_prefix": "2",
      "overview_label_title": "Sessions"
    }
  ],
  "overview_metadata": {
    "overview_number": 1,
    "overview_title": "Model Behavior",
    "overview_subtitle": "Using Quadratic Functions to Model Data",
    "overview_description": "In this lesson, students determine a quadratic regression that best models a table of data and make predictions using the equation. They model a real-world data set using a linear, quadratic, or exponential function and make their decision based on the scatter plot, the correlation coefficient (r-value), the <math><msup><mi>r</mi><mn>2</mn></msup></math>-value of the regression equation or each function, and the context. They then use their regression equation to make predictions and interpret the results in context."
  },
  "overview_items": [
    {
      "overview_item_type": "learning_goals",
      "overview_item_content_type": "html",
      "overview_item_title": "My Learning Goals",
      "overview_item_data": {
        "overview_item_data_type": "list",
        "overview_item_data_items": [
          "I can use two variables represented in a scatter plot are related.",
          "I can use quadratic functions to make predictions about data in context."
        ]
      }
    },
    {
      "overview_item_type": "big_ideas",
      "overview_item_content_type": "text",
      "overview_item_title": "Big Idea",
      "overview_item_data": {
        "overview_item_data_type": "list",
        "overview_item_data_items": [
          "Investigate Data",
          "Model with Functions"
        ]
      }
    },
    {
      "overview_item_type": "essential_ideas",
      "overview_item_content_type": "html",
      "overview_item_title": "Essential Ideas",
      "overview_item_data": {
        "overview_item_data_type": "list",
        "overview_item_data_items": [
          "A quadratic regression equation can model certain real-world data sets. You can use the regression equation to make predictions. However, there may be limitations on the domain, depending on the situation.",
          "The best mathematical model for a situation may not always be the most obvious one. After testing your solution, you may need to make revisions."
        ]
      }
    },
    {
      "overview_item_type": "key_terms",
      "overview_item_content_type": "text",
      "overview_item_title": "Key Terms",
      "overview_item_data": {
        "overview_item_data_type": "group_list",
        "overview_item_data_items": [
          {
            "overview_item_data_group_title": "Activity 1",
            "overview_item_data_group_items": []
          },
          {
            "overview_item_data_group_title": "Activity 2",
            "overview_item_data_group_items": []
          },
          {
            "overview_item_data_group_title": "Activity 3",
            "overview_item_data_group_items": []
          }
        ]
      }
    },
    {
      "overview_item_type": "pacing_guide",
      "overview_item_content_type": "text",
      "overview_item_title": "Lesson Structure and Pacing Guide",
      "overview_item_data": {
        "overview_item_data_type": "session_list",
        "overview_item_data_items": [
          {
            "overview_item_data_group_title": "Session 1",
            "overview_item_data_groups": [
              {
                "overview_item_data_group_title": "Activate",
                "overview_item_data_group_items": [
                  {
                    "overview_item_data_group_item_type": "presentation",
                    "overview_item_data_group_item_title": "I'm Noticing a Trend . . .",
                    "overview_item_data_group_item_description": "Students examine a table and a scatter plot to notice trends in the data.",
                    "overview_item_data_group_item_pacing": {
                      "pacing_type": "minutes",
                      "pacing_amount": 5
                    }
                  }
                ]
              },
              {
                "overview_item_data_group_title": "Explore and Develop",
                "overview_item_data_group_items": [
                  {
                    "overview_item_data_group_item_type": "book",
                    "overview_item_data_group_item_prefix": "Activity 1",
                    "overview_item_data_group_item_title": "Using Quadratic Functions to Model Data",
                    "overview_item_data_group_item_description": "Students analyze data related to a context and use the data to determine a regression equation.",
                    "overview_item_data_group_item_pacing": {
                      "pacing_type": "minutes",
                      "pacing_amount": 20
                    }
                  },
                  {
                    "overview_item_data_group_item_type": "book",
                    "overview_item_data_group_item_prefix": "Activity 2",
                    "overview_item_data_group_item_title": "Analyzing a Quadratic Model",
                    "overview_item_data_group_item_description": "Students analyze a quadratic model and use it to answer real-world problems.",
                    "overview_item_data_group_item_pacing": {
                      "pacing_type": "minutes",
                      "pacing_amount": 15
                    }
                  }
                ]
              }
            ]
          },
          {
            "overview_item_data_group_title": "Session 2",
            "overview_item_data_groups": [
              {
                "overview_item_data_group_title": "Explore and Develop",
                "overview_item_data_group_items": [
                  {
                    "overview_item_data_group_item_type": "book",
                    "overview_item_data_group_item_prefix": "Activity 3",
                    "overview_item_data_group_item_title": "Using Regressions to Model Data",
                    "overview_item_data_group_item_description": "Students model a situation and interpret the reasonableness of a prediction based upon the situation.",
                    "overview_item_data_group_item_pacing": {
                      "pacing_type": "minutes",
                      "pacing_amount": 30
                    }
                  }
                ]
              },
              {
                "overview_item_data_group_title": "Reflect",
                "overview_item_data_group_items": [
                  {
                    "overview_item_data_group_item_type": "book",
                    "overview_item_data_group_item_title": "The Model Decision",
                    "overview_item_data_group_item_description": "Students explain how to determine whether a linear, quadratic, or exponential model best fits a data set.",
                    "overview_item_data_group_item_pacing": {
                      "pacing_type": "minutes",
                      "pacing_amount": 10
                    }
                  }
                ]
              }
            ]
          }
        ]
      }
    },
    {
      "overview_item_type": "materials_needed",
      "overview_item_content_type": "text",
      "overview_item_title": "Materials Needed",
      "overview_item_data": {
        "overview_item_data_type": "list",
        "overview_item_data_items": [
          "If facilitating this lesson without student devices, no additional materials are needed.",
          "To avoid printing additional materials not included in MATHbook (like Activate activities and Session Quick Checks) project them using the Present button above."
        ]
      }
    }
  ]
}